[
  {
    "src": "images/brabanson/photo_2023-02-08_17-29-47.jpg",
    "thumb": "images/brabanson/photo_2023-02-08_17-29-47.jpg",
    "header": "Сьогодні Пті вперше відвідав пляж зі мною! Він дуже задоволений та веселий, навіть купався в морі.",
    "description": "",
    "date": 202302081722
  },
  {
    "src": "images/brabanson/photo_2023-02-08_17-30-06.jpg",
    "thumb": "images/brabanson/photo_2023-02-08_17-30-06.jpg",
    "header": "Ми відкрили нову тренувальну ділянку для Пті! Він дуже захоплюється новими задачами та іграми.",
    "description": "",
    "date": 202302081713
  },
  {
    "src": "images/brabanson/photo_2023-02-08_17-30-12.jpg",
    "thumb": "images/brabanson/photo_2023-02-08_17-30-12.jpg",
    "header": "Ми відкрили нову тренувальну ділянку для Пті! Він дуже захоплюється новими задачами та іграми.",
    "description": "",
    "date": 202302081729
  },
  {
    "src": "images/brabanson/photo_2023-02-08_17-30-16.jpg",
    "thumb": "images/brabanson/photo_2023-02-08_17-30-16.jpg",
    "header": "Сьогодні Пті вперше відвідав пляж зі мною! Він дуже задоволений та веселий, навіть купався в морі.",
    "description": "",
    "date": 202302081746
  },
  {
    "src": "images/brabanson/photo_2023-02-08_17-30-20.jpg",
    "thumb": "images/brabanson/photo_2023-02-08_17-30-20.jpg",
    "header": "Ми відкрили нову тренувальну ділянку для Пті! Він дуже захоплюється новими задачами та іграми.",
    "description": "",
    "date": 202303011725
  },
  {
    "src": "images/brabanson/photo_2023-02-08_17-30-24.jpg",
    "thumb": "images/brabanson/photo_2023-02-08_17-30-24.jpg",
    "header": "Ми відкрили нову тренувальну ділянку для Пті! Він дуже захоплюється новими задачами та іграми.",
    "description": "",
    "date": 202302081628
  },
  {
    "src": "images/brabanson/photo_2023-02-08_17-30-39.jpg",
    "thumb": "images/brabanson/photo_2023-02-08_17-30-39.jpg",
    "header": "Ми відкрили нову тренувальну ділянку для Пті! Він дуже захоплюється новими задачами та іграми.",
    "description": "",
    "date": 202302081720
  },
  {
    "src": "images/brabanson/photo_2023-02-08_17-30-42.jpg",
    "thumb": "images/brabanson/photo_2023-02-08_17-30-42.jpg",
    "header": "Сьогодні Пті вперше відвідав пляж зі мною! Він дуже задоволений та веселий, навіть купався в морі.",
    "description": "",
    "date": 202302081731
  }
]
